examples/__init__.py
examples/run_nordic_example.py
examples/nordic_blinky/__init__.py
examples/nordic_blinky/config.py
examples/nordic_blinky/verify_fixes.py
test_a_ble/__init__.py
test_a_ble/ble_manager.py
test_a_ble/cli.py
test_a_ble/test_context.py
test_a_ble/test_runner.py
tests/__init__.py
tests/test_ble_manager.py
tests/test_cli.py
tests/test_test_context.py
tests/test_test_discovery.py
tests/test_test_runner.py
tests/test_discovery_test_package/__init__.py
test_a_ble-0.1.0.dist-info/LICENSE
test_a_ble-0.1.0.dist-info/METADATA
test_a_ble-0.1.0.dist-info/WHEEL
test_a_ble-0.1.0.dist-info/entry_points.txt
test_a_ble-0.1.0.dist-info/top_level.txt
test_a_ble-0.1.0.dist-info/RECORD
