Metadata-Version: 2.2
Name: test-a-ble
Version: 0.1.0
Summary: Framework for testing BLE IoT devices
Home-page: https://github.com/nrb-tech/test-a-ble
Author: Nick Brook
Author-email: nick@nrbtech.io
Keywords: bluetooth,ble,iot,testing,automation
Classifier: Development Status :: 3 - Alpha
Classifier: Intended Audience :: Developers
Classifier: License :: OSI Approved :: MIT License
Classifier: Programming Language :: Python :: 3
Classifier: Programming Language :: Python :: 3.12
Classifier: Programming Language :: Python :: 3.13
Classifier: Topic :: Software Development :: Testing
Classifier: Topic :: System :: Hardware
Requires-Python: >=3.12
License-File: LICENSE
Requires-Dist: bleak>=0.22.3
Requires-Dist: rich>=13.9.4
Requires-Dist: packaging
Requires-Dist: prompt_toolkit>=3.0.0
Provides-Extra: test
Requires-Dist: pytest>=8.3.5; extra == "test"
Requires-Dist: pytest-cov>=6.0.0; extra == "test"
Requires-Dist: pytest-asyncio>=0.22.0; extra == "test"
Requires-Dist: tox>=4.24.2; extra == "test"
Provides-Extra: lint
Requires-Dist: black>=25.1.0; extra == "lint"
Requires-Dist: isort>=6.0.1; extra == "lint"
Requires-Dist: flake8>=7.1.2; extra == "lint"
Requires-Dist: flake8-docstrings>=1.7.0; extra == "lint"
Requires-Dist: flake8-pyproject>=1.2.3; extra == "lint"
Requires-Dist: mypy>=1.15.0; extra == "lint"
Provides-Extra: security
Requires-Dist: bandit>=1.8.3; extra == "security"
Requires-Dist: safety>=3.3.1; extra == "security"
Provides-Extra: docs
Requires-Dist: sphinx>=8.2.3; extra == "docs"
Requires-Dist: sphinx-rtd-theme>=3.0.2; extra == "docs"
Requires-Dist: myst-parser>=4.0.1; extra == "docs"
Provides-Extra: build
Requires-Dist: twine>=6.1.0; extra == "build"
Requires-Dist: build>=1.2.2; extra == "build"
Provides-Extra: dev
Requires-Dist: pytest>=8.3.5; extra == "dev"
Requires-Dist: pytest-cov>=6.0.0; extra == "dev"
Requires-Dist: pytest-asyncio>=0.22.0; extra == "dev"
Requires-Dist: tox>=4.24.2; extra == "dev"
Requires-Dist: black>=25.1.0; extra == "dev"
Requires-Dist: isort>=6.0.1; extra == "dev"
Requires-Dist: flake8>=7.1.2; extra == "dev"
Requires-Dist: flake8-docstrings>=1.7.0; extra == "dev"
Requires-Dist: flake8-pyproject>=1.2.3; extra == "dev"
Requires-Dist: mypy>=1.15.0; extra == "dev"
Requires-Dist: bandit>=1.8.3; extra == "dev"
Requires-Dist: safety>=3.3.1; extra == "dev"
Requires-Dist: sphinx>=8.2.3; extra == "dev"
Requires-Dist: sphinx-rtd-theme>=3.0.2; extra == "dev"
Requires-Dist: myst-parser>=4.0.1; extra == "dev"
Requires-Dist: twine>=6.1.0; extra == "dev"
Requires-Dist: build>=1.2.2; extra == "dev"
Dynamic: author
Dynamic: author-email
Dynamic: classifier
Dynamic: description
Dynamic: description-content-type
Dynamic: home-page
Dynamic: keywords
Dynamic: provides-extra
Dynamic: requires-dist
Dynamic: requires-python
Dynamic: summary
